pygol/audio/__init__.py
pygol/drawable/__init__.py
pygol/routine/__init__.py
pygol/ui/__init__.py
pygol_engine-0.7.1.dist-info/METADATA
pygol_engine-0.7.1.dist-info/WHEEL
pygol_engine-0.7.1.dist-info/top_level.txt
pygol_engine-0.7.1.dist-info/RECORD
