Metadata-Version: 2.1
Name: pygol-engine
Version: 0.7.1
Author: Monsler
Author-email: galileoru22@gmail.com
License: MIT
Classifier: Programming Language :: Python :: 3
Classifier: License :: OSI Approved :: MIT License
Classifier: Operating System :: OS Independent
